AvWeather/__init__.py
AvWeather/app.py
AvWeather-1.dist-info/LICENSE.txt
AvWeather-1.dist-info/METADATA
AvWeather-1.dist-info/WHEEL
AvWeather-1.dist-info/top_level.txt
AvWeather-1.dist-info/RECORD
