Metadata-Version: 2.1
Name: AvWeather
Version: 1
Summary: Aviation METAR and TAF Reports
Home-page: https://github.com/siddharth-tewari/AvWeather
Author: Siddharth Tewari
License: MIT
Download-URL: https://github.com/siddharth-tewari/AvWeather/archive/refs/tags/0.1.tar.gz
Keywords: Aviation,Aviation Weather,Metar,TAF
Platform: UNKNOWN
License-File: LICENSE.txt
